{"parent":"minecraft:item/handheld","textures":{"layer0":"minecraft:item/diamond_sword"},"overrides":[{"predicate":{"custom_model_data":200000},"model":"iaalchemy:auto_generated/mysterious_sword"},{"predicate":{"custom_model_data":200001},"model":"iasurvival:auto_generated/vyderlight_sword"},{"predicate":{"custom_model_data":200002},"model":"iasurvival:auto_generated/dark_amethyst_sword"},{"predicate":{"custom_model_data":200003},"model":"iasurvival:auto_generated/end_sword"},{"predicate":{"custom_model_data":200004},"model":"iasurvival:auto_generated/bronze_sword"},{"predicate":{"custom_model_data":200005},"model":"iasurvival:auto_generated/emerald_sword"},{"predicate":{"custom_model_data":200006},"model":"iasurvival:item/swords/firesword_sword"},{"predicate":{"custom_model_data":200007},"model":"iaspecial_swords:auto_generated/elucidator_sword"},{"predicate":{"custom_model_data":200008},"model":"iasurvival:auto_generated/rusteroth_sword"},{"predicate":{"custom_model_data":200009},"model":"iasurvival:auto_generated/aqualight_sword"},{"predicate":{"custom_model_data":200010},"model":"iaspecial_swords:auto_generated/repulser_sword"},{"predicate":{"custom_model_data":200011},"model":"iaspecial_swords:item/floating_sword"},{"predicate":{"custom_model_data":200012},"model":"iasurvival:auto_generated/bloodnite_sword"},{"predicate":{"custom_model_data":200013},"model":"iaspecial_swords:item/masters_sword"},{"predicate":{"custom_model_data":200014},"model":"iasurvival:auto_generated/ruby_sword"},{"predicate":{"custom_model_data":200015},"model":"iaspecial_swords:item/closed_lightsaber"},{"predicate":{"custom_model_data":200016},"model":"iaspecial_swords:item/green_lightsaber"},{"predicate":{"custom_model_data":200017},"model":"iaspecial_swords:item/red_lightsaber"},{"predicate":{"custom_model_data":200018},"model":"iaspecial_swords:item/blue_lightsaber"},{"predicate":{"custom_model_data":200019},"model":"bettermobs:auto_generated/amethyst_diamond_sword"},{"predicate":{"custom_model_data":200020},"model":"itembound:auto_generated/daggerdiamond"},{"predicate":{"custom_model_data":200021},"model":"itembound:auto_generated/rapierdiamond"},{"predicate":{"custom_model_data":200022},"model":"itembound:auto_generated/master_sword"},{"predicate":{"custom_model_data":200023},"model":"itembound:auto_generated/katanadiamond"},{"predicate":{"custom_model_data":200024},"model":"3dfantasyweaponscit:item/katana/azure_sabre"},{"predicate":{"custom_model_data":200025},"model":"3dfantasyweaponscit:item/katana/bloody_vengeance_blade"},{"predicate":{"custom_model_data":200026},"model":"3dfantasyweaponscit:item/dagger/azure_shortsword"},{"predicate":{"custom_model_data":200027},"model":"3dfantasyweaponscit:item/axe/azure_greataxe"},{"predicate":{"custom_model_data":200028},"model":"3dfantasyweaponscit:item/axe/skeleton_axe"},{"predicate":{"custom_model_data":200029},"model":"3dfantasyweaponscit:item/axe/treacherous_axe"},{"predicate":{"custom_model_data":200030},"model":"3dfantasyweaponscit:item/scythe/azure_scythe"},{"predicate":{"custom_model_data":200031},"model":"3dfantasyweaponscit:item/greatsword/claymore"},{"predicate":{"custom_model_data":200032},"model":"3dfantasyweaponscit:item/greatsword/crimson_cleaver"},{"predicate":{"custom_model_data":200033},"model":"3dfantasyweaponscit:item/greatsword/treacherous_cleaver"},{"predicate":{"custom_model_data":200034},"model":"3dfantasyweaponscit:item/lance/piercer"},{"predicate":{"custom_model_data":200035},"model":"3dfantasyweaponscit:item/lance/runic_piercer"},{"predicate":{"custom_model_data":200036},"model":"3dfantasyweaponscit:item/lance/iron_polearm"},{"predicate":{"custom_model_data":200037},"model":"3dfantasyweaponscit:item/hammer/treacherous_bludgeon"},{"predicate":{"custom_model_data":200038},"model":"3dfantasyweaponscit:item/hammer/wooden_bludgeon"},{"predicate":{"custom_model_data":200039},"model":"3dfantasyweaponscit:item/hammer/iron_mace"},{"predicate":{"custom_model_data":200040},"model":"3dfantasyweaponscit:item/hammer/vindicator"},{"predicate":{"custom_model_data":200041},"model":"3dfantasyweaponscit:item/swords/azure_greatsword"},{"predicate":{"custom_model_data":200042},"model":"3dfantasyweaponscit:item/swords/dragon_sword"},{"predicate":{"custom_model_data":200043},"model":"3dfantasyweaponscit:item/swords/spider_sword"},{"predicate":{"custom_model_data":200044},"model":"3dfantasyweaponscit:item/swords/demonic_sword"},{"predicate":{"custom_model_data":200045},"model":"3dfantasyweaponscit:item/swords/nature_sword"},{"predicate":{"custom_model_data":200046},"model":"minecraft:item/diamond_sword"}]}